{
  "topKeywords": [
    [
      "网页链接",
      22
    ],
    [
      "期待",
      18
    ],
    [
      "爱奇艺",
      17
    ],
    [
      "云秀行",
      14
    ],
    [
      "任嘉伦",
      10
    ]
  ],
  "topItems": [
    {
      "title": "#刘宇宁云秀行插曲何故# 今日上线。\n赤诚赴爱。不问因果缘由。\n独饮往事。自省情起何故。\n一起来@爱奇艺 看#云秀行何故...",
      "content": "#刘宇宁云秀行插曲何故# 今日上线。\n赤诚赴爱。不问因果缘由。\n独饮往事。自省情起何故。\n一起来@爱奇艺 看#云秀行何故MV##云秀行#。聆听心底难言的遗憾。L云秀行官微的微博视频\n@酷狗音乐 O网页链接\n@QQ音乐 O网页链接\n@酷我音乐 O网页链接 ​",
      "author": "摩登兄弟刘宇宁",
      "time": "06月19日 12:25",
      "likes": "492366",
      "link": "https://weibo.com/5456865382/R4P6dkA2a?refer_flag=1001030103_",
      "platform": "weibo",
      "summary": "#刘宇宁云秀行插曲何故# 今日上线。\n赤诚赴爱。不问因果缘由。\n独饮往事。自省情起何故。\n一起来@爱奇艺 看#云秀行何故MV##云秀行#。聆听心底难言的遗憾。L云秀行官微的微博视频\n@酷狗音乐 O网页链接\n@QQ音乐 O网页链接\n@酷我音乐 O网页链接 ​",
      "likeCount": 492366
    },
    {
      "title": "爱奇艺纳逗Pro艺人库建立的初衷，旨在为AIGC创作者提供一个规范的平台，便于其在创作中遴选艺人，并通过爱奇艺与艺人方高...",
      "content": "爱奇艺纳逗Pro艺人库建立的初衷，旨在为AIGC创作者提供一个规范的平台，便于其在创作中遴选艺人，并通过爱奇艺与艺人方高效沟通合作细节。目前，已有100多位深度合作艺人同意入驻爱奇艺纳逗Pro艺人库。\n需要强调的是，入驻爱奇艺纳逗Pro艺人库，代表艺人有接洽AI影视项目的意愿，但是否参加某个具体项 ​ 展开c",
      "author": "爱奇艺",
      "time": "04月20日 16:35",
      "likes": "45706",
      "link": "https://weibo.com/1731986465/QBGyndtEU?refer_flag=1001030103_",
      "platform": "weibo",
      "summary": "爱奇艺纳逗Pro艺人库建立的初衷，旨在为AIGC创作者提供一个规范的平台，便于其在创作中遴选艺人，并通过爱奇艺与艺人方高效沟通合作细节。目前，已有100多位深度合作艺人同意入驻爱奇艺纳逗Pro艺人库。\n需要强调的是，入驻爱奇艺纳逗Pro艺人库，代表艺人有接洽AI影视项目的意愿，但是否参加某个具体项 ",
      "likeCount": 45706
    },
    {
      "title": "丁禹兮超话\n万千热爱，汇聚九千热度🔥\n谢谢每一位跟随海虾@丁禹兮 探寻真相的你，所有支持与陪伴尽数收下，前路探案之旅...",
      "content": "丁禹兮超话\n万千热爱，汇聚九千热度🔥\n谢谢每一位跟随海虾@丁禹兮 探寻真相的你，所有支持与陪伴尽数收下，前路探案之旅，我们继续同行！\n恭喜爱奇艺站内热度破9️⃣0️⃣0️⃣0️⃣🔥\n#丁禹兮##丁禹兮张海虾##丁禹兮南部档案# ​​​​",
      "author": "丁禹兮工作室_OFFICIAL",
      "time": "06月19日 18:37",
      "likes": "28840",
      "link": "https://weibo.com/6822431581/R4Rx8i8R5?refer_flag=1001030103_",
      "platform": "weibo",
      "summary": "丁禹兮超话\n万千热爱，汇聚九千热度🔥\n谢谢每一位跟随海虾@丁禹兮 探寻真相的你，所有支持与陪伴尽数收下，前路探案之旅，我们继续同行！\n恭喜爱奇艺站内热度破9️⃣0️⃣0️⃣0️⃣🔥\n#丁禹兮##丁禹兮张海虾##丁禹兮南部档案# ​​​​",
      "likeCount": 28840
    }
  ],
  "totalLikes": 614729,
  "avgLikes": 30736,
  "sentiment": {
    "positive": 7,
    "negative": 0,
    "neutral": 15,
    "positivePercent": 32,
    "negativePercent": 0,
    "neutralPercent": 68
  }
}