{
  "topKeywords": [
    [
      "灵魂摆渡",
      33
    ],
    [
      "十年",
      14
    ],
    [
      "展开",
      11
    ],
    [
      "想把你和",
      10
    ],
    [
      "时间藏起",
      10
    ]
  ],
  "topItems": [
    {
      "title": "爱奇艺古装剧《念相思》\n主演：虞书欣、侯明昊、古子成\n导演：钟青《花间令》\n编剧：赵天佑、应志南《柳舟记》\n造型：易小雅...",
      "content": "爱奇艺古装剧《念相思》\n主演：虞书欣、侯明昊、古子成\n导演：钟青《花间令》\n编剧：赵天佑、应志南《柳舟记》\n造型：易小雅《苍兰诀》\n6月30日横店开机，10月全剧杀青。\n\n简介：根据一度君华小说《神仙肉》改编。 清虚观知观容尘子道长乃禄存星君转世，不仅是个品行高洁的正人君子，其身体血肉更对妖 展开c",
      "author": "朱红院",
      "time": "05月30日 17:35",
      "likes": "48351",
      "link": "https://weibo.com/2949989907/R1OA3FDYc?refer_flag=1001030103_",
      "platform": "weibo",
      "summary": "爱奇艺古装剧《念相思》\n主演：虞书欣、侯明昊、古子成\n导演：钟青《花间令》\n编剧：赵天佑、应志南《柳舟记》\n造型：易小雅《苍兰诀》\n6月30日横店开机，10月全剧杀青。\n\n简介：根据一度君华小说《神仙肉》改编。 清虚观知观容尘子道长乃禄存星君转世，不仅是个品行高洁的正人君子，其身体血肉更对妖 展开c",
      "likeCount": 48351
    },
    {
      "title": "爱奇艺纳逗Pro艺人库建立的初衷，旨在为AIGC创作者提供一个规范的平台，便于其在创作中遴选艺人，并通过爱奇艺与艺人方高...",
      "content": "爱奇艺纳逗Pro艺人库建立的初衷，旨在为AIGC创作者提供一个规范的平台，便于其在创作中遴选艺人，并通过爱奇艺与艺人方高效沟通合作细节。目前，已有100多位深度合作艺人同意入驻爱奇艺纳逗Pro艺人库。\n需要强调的是，入驻爱奇艺纳逗Pro艺人库，代表艺人有接洽AI影视项目的意愿，但是否参加某个具体项 展开c",
      "author": "爱奇艺",
      "time": "04月20日 16:35",
      "likes": "45745",
      "link": "https://weibo.com/1731986465/QBGyndtEU?refer_flag=1001030103_",
      "platform": "weibo",
      "summary": "爱奇艺纳逗Pro艺人库建立的初衷，旨在为AIGC创作者提供一个规范的平台，便于其在创作中遴选艺人，并通过爱奇艺与艺人方高效沟通合作细节。目前，已有100多位深度合作艺人同意入驻爱奇艺纳逗Pro艺人库。\n需要强调的是，入驻爱奇艺纳逗Pro艺人库，代表艺人有接洽AI影视项目的意愿，但是否参加某个具体项 ",
      "likeCount": 45745
    },
    {
      "title": "#想把你和时间藏起来时差回响杀青特辑# #想把你和时间藏起来杀青# 恰逢其时的相遇，思绪辗转的重逢。宿命拨弄分秒时差，心...",
      "content": "#想把你和时间藏起来时差回响杀青特辑# #想把你和时间藏起来杀青# 恰逢其时的相遇，思绪辗转的重逢。宿命拨弄分秒时差，心跳回响，爱意永恒。#想把你和时间藏起来#\n@爱奇艺 心动预约：O网页链接\nL《想把你和时间藏起来》时差回响杀青特辑",
      "author": "想把你和时间藏起来官微",
      "time": "06月01日 12:00",
      "likes": "16617",
      "link": "https://weibo.com/7311580609/R25eVEJmT?refer_flag=1001030103_",
      "platform": "weibo",
      "summary": "#想把你和时间藏起来时差回响杀青特辑# #想把你和时间藏起来杀青# 恰逢其时的相遇，思绪辗转的重逢。宿命拨弄分秒时差，心跳回响，爱意永恒。#想把你和时间藏起来#\n@爱奇艺 心动预约：O网页链接\nL《想把你和时间藏起来》时差回响杀青特辑",
      "likeCount": 16617
    }
  ],
  "totalLikes": 141520,
  "avgLikes": 10109,
  "sentiment": {
    "positive": 3,
    "negative": 0,
    "neutral": 18,
    "positivePercent": 14,
    "negativePercent": 0,
    "neutralPercent": 86
  }
}